events/__init__.py
devpie_client_events-0.0.28.dist-info/METADATA
devpie_client_events-0.0.28.dist-info/WHEEL
devpie_client_events-0.0.28.dist-info/top_level.txt
devpie_client_events-0.0.28.dist-info/RECORD
