Metadata-Version: 2.1
Name: devpie-client-events
Version: 0.0.28
Summary: UNKNOWN
Home-page: https://github.com/ivorscott/devpie-client-events
Author: ivorscott
Author-email: ivor@devpie.io
License: UNKNOWN
Platform: UNKNOWN
Classifier: Programming Language :: Python :: 3
Classifier: License :: OSI Approved :: MIT License
Classifier: Operating System :: OS Independent
Requires-Python: >=3.6
